atac_mapper/__init__.py
atac_mapper/reference_mapping/mapping_atac.py
atac_mapper/topic_matching/__init__.py
atac_mapper/topic_matching/topic_match.py
atac_mapper/topic_matching/utils.py
atac_mapper-0.1.0.dist-info/licenses/LICENSE
atac_mapper-0.1.0.dist-info/METADATA
atac_mapper-0.1.0.dist-info/WHEEL
atac_mapper-0.1.0.dist-info/top_level.txt
atac_mapper-0.1.0.dist-info/RECORD
