Metadata-Version: 2.4
Name: atac-mapper
Version: 0.1.0
Summary: Map query scATAC-seq data to a single-cell chromatin accessibility atlas
Author: Nadezhda Azbukina
Maintainer-email: Nadezhda Azbukina <nazbukina@ethz.ch>
License: MIT License
Classifier: Programming Language :: Python :: 3 :: Only
Classifier: Programming Language :: Python :: 3.9
Classifier: Programming Language :: Python :: 3.10
Classifier: Programming Language :: Python :: 3.11
Classifier: Programming Language :: Python :: 3.12
Classifier: Programming Language :: Python :: 3.13
Requires-Python: >=3.9
License-File: LICENSE
Requires-Dist: cellmapper>=0.1
Requires-Dist: cloudpickle>=2.2
Requires-Dist: joblib>=1.3
Requires-Dist: numpy>=1.24
Requires-Dist: pandas>=2
Requires-Dist: scanpy>=1.11
Requires-Dist: scarches>=0.5
Requires-Dist: scipy>=1.11
Requires-Dist: scvi-tools>=1
Requires-Dist: torch>=2
Provides-Extra: dev
Requires-Dist: pre-commit; extra == "dev"
Requires-Dist: pytest>=7; extra == "dev"
Requires-Dist: pytest-cov; extra == "dev"
Provides-Extra: doc
Requires-Dist: myst-nb>=1; extra == "doc"
Requires-Dist: sphinx>=8; extra == "doc"
Requires-Dist: sphinx-autodoc-typehints>=3; extra == "doc"
Requires-Dist: sphinx-book-theme>=1.1; extra == "doc"
Requires-Dist: sphinx-copybutton; extra == "doc"
Requires-Dist: sphinx-tabs; extra == "doc"
Requires-Dist: sphinxcontrib-bibtex>=2.6; extra == "doc"
Requires-Dist: sphinxext-opengraph; extra == "doc"
Provides-Extra: test
Requires-Dist: pytest>=7; extra == "test"
Requires-Dist: pytest-cov; extra == "test"
Dynamic: license-file
